whl2pyz.py
whl2pyz-0.0.5.dist-info/licenses/LICENSE
whl2pyz-0.0.5.dist-info/METADATA
whl2pyz-0.0.5.dist-info/WHEEL
whl2pyz-0.0.5.dist-info/entry_points.txt
whl2pyz-0.0.5.dist-info/top_level.txt
whl2pyz-0.0.5.dist-info/RECORD
